kpoints_generator/__init__.py
kpoints_generator/cli.py
kpoints_generator/core.py
kpoints_generator/logs.py
kpoints_generator/java_resources/GridGenerator.jar
kpoints_generator/java_resources/getKPoints
kpoints_generator/java_resources/minDistanceCollections/Gamma/lattices_G_18_5832_2019.8.1
kpoints_generator/java_resources/minDistanceCollections/Gamma/lattices_G_19_5832_2019.8.1
kpoints_generator/java_resources/minDistanceCollections/Gamma/lattices_G_20_5832_2019.8.1
kpoints_generator/java_resources/minDistanceCollections/Gamma/lattices_G_21_5832_2019.8.1
kpoints_generator/java_resources/minDistanceCollections/Gamma/lattices_G_26_5832_2019.8.1
kpoints_generator/java_resources/minDistanceCollections/Gamma/lattices_G_27_5832_2019.8.1
kpoints_generator/java_resources/minDistanceCollections/Gamma/lattices_G_36_5832_2019.8.1
kpoints_generator/java_resources/minDistanceCollections/Gamma/lattices_G_37_5832_2019.8.1
kpoints_generator/java_resources/minDistanceCollections/Gamma/lattices_G_40_5832_2019.8.1
kpoints_generator/java_resources/minDistanceCollections/Gamma/lattices_G_41_5832_2019.8.1
kpoints_generator/java_resources/minDistanceCollections/Gamma/lattices_G_48_5832_2019.8.1
kpoints_generator/java_resources/minDistanceCollections/Gamma/lattices_G_49_5832_2019.8.1
kpoints_generator/java_resources/minDistanceCollections/Gamma/lattices_G_50_5832_2019.8.1
kpoints_generator/java_resources/minDistanceCollections/Gamma/lattices_G_53_5832_2019.8.1
kpoints_generator/java_resources/minDistanceCollections/Gamma/lattices_G_58_5832_2019.8.1
kpoints_generator/java_resources/minDistanceCollections/Gamma/lattices_G_62_46656_2019.8.1
kpoints_generator/java_resources/minDistanceCollections/Gamma/lattices_G_63_46656_2019.8.1
kpoints_generator/java_resources/minDistanceCollections/Gamma/lattices_G_64_46656_2019.8.1
kpoints_generator/java_resources/minDistanceCollections/Gamma/lattices_G_71_46656_2019.8.1
kpoints_generator-0.3.0.dist-info/licenses/LICENSE-APACHE
kpoints_generator-0.3.0.dist-info/METADATA
kpoints_generator-0.3.0.dist-info/WHEEL
kpoints_generator-0.3.0.dist-info/entry_points.txt
kpoints_generator-0.3.0.dist-info/top_level.txt
kpoints_generator-0.3.0.dist-info/RECORD
