Metadata-Version: 2.4
Name: kpoints_generator
Version: 0.3.0
Summary: A Python wrapper for the k-point grid generator Java package
Author: Mik Luki
License-Expression: Apache-2.0
Project-URL: Homepage, https://github.com/Mikluki/kpoints_generator_mueller
Keywords: vasp,kpoints,dft,computational-chemistry
Classifier: Programming Language :: Python :: 3
Classifier: Operating System :: OS Independent
Classifier: Topic :: Scientific/Engineering :: Chemistry
Classifier: Topic :: Scientific/Engineering :: Physics
Requires-Python: >=3.6
License-File: LICENSE-APACHE
Dynamic: license-file
